src/__init__.py
src/data_cleaner/__init__.py
src/data_cleaner/configs.py
src/data_cleaner/helpers.py
src/data_cleaner/services.py
src/tests/__init__.py
src/tests/test_helpers.py
src/tests/test_services.py
reply_ai_data_processing-0.0.1.dist-info/LICENSE
reply_ai_data_processing-0.0.1.dist-info/METADATA
reply_ai_data_processing-0.0.1.dist-info/WHEEL
reply_ai_data_processing-0.0.1.dist-info/top_level.txt
reply_ai_data_processing-0.0.1.dist-info/RECORD
